mp3art/__init__.py
mp3art/mp3art.py
mp3art-1.0.3.dist-info/METADATA
mp3art-1.0.3.dist-info/WHEEL
mp3art-1.0.3.dist-info/entry_points.txt
mp3art-1.0.3.dist-info/top_level.txt
mp3art-1.0.3.dist-info/RECORD
