Metadata-Version: 2.2
Name: mp3art
Version: 1.0.3
Summary:  A terminal command to add or remove cover art for MP3 files.
Home-page: https://github.com/rynstwrt/mp3art
Author: rynstwrt
Requires-Dist: mutagen~=1.47.0
Requires-Dist: setuptools~=75.8.0
Dynamic: author
Dynamic: description
Dynamic: description-content-type
Dynamic: home-page
Dynamic: requires-dist
Dynamic: summary
